dataspot/__init__.py
dataspot/core.py
dataspot/exceptions.py
dataspot/analyzers/__init__.py
dataspot/analyzers/analyzer.py
dataspot/analyzers/base.py
dataspot/analyzers/compare.py
dataspot/analyzers/discovery.py
dataspot/analyzers/filters.py
dataspot/analyzers/finder.py
dataspot/analyzers/pattern_extractor.py
dataspot/analyzers/preprocessors.py
dataspot/analyzers/stats.py
dataspot/analyzers/tree.py
dataspot/models/__init__.py
dataspot/models/analyzer.py
dataspot/models/compare.py
dataspot/models/discovery.py
dataspot/models/finder.py
dataspot/models/pattern.py
dataspot/models/tree.py
dataspot-0.4.6.dist-info/METADATA
dataspot-0.4.6.dist-info/WHEEL
dataspot-0.4.6.dist-info/licenses/LICENSE
dataspot-0.4.6.dist-info/RECORD
